flox/__init__.py
flox/browser.py
flox/clipboard.py
flox/launcher.py
flox/settings.py
flox/string_matcher.py
flox/utils.py
flox/version
Flox_lib-0.20.0.dist-info/LICENSE.txt
Flox_lib-0.20.0.dist-info/METADATA
Flox_lib-0.20.0.dist-info/WHEEL
Flox_lib-0.20.0.dist-info/top_level.txt
Flox_lib-0.20.0.dist-info/zip-safe
Flox_lib-0.20.0.dist-info/RECORD
