Metadata-Version: 2.1
Name: Flox-lib
Version: 0.20.0
Summary: Python library to help build Flow Launcher and Wox plugins.
Home-page: https://github.com/Garulf/Flox
Author: William McAllister
Author-email: dev.garulf@gmail.com
License: MIT
Project-URL: Bug Tracker, https://github.com/Garulf/Flox/issues
Classifier: Programming Language :: Python :: 3
Classifier: License :: OSI Approved :: MIT License
Classifier: Operating System :: Microsoft :: Windows
License-File: LICENSE.txt
